scaliger/__init__.py
scaliger-0.0.1.dist-info/licenses/LICENSE
scaliger-0.0.1.dist-info/METADATA
scaliger-0.0.1.dist-info/WHEEL
scaliger-0.0.1.dist-info/top_level.txt
scaliger-0.0.1.dist-info/RECORD
