Metadata-Version: 2.4
Name: scaliger
Version: 0.0.1
Summary: Semantic Codegen for BEDA and TEI P5 archives.
Author-email: Andrea Marruzzo <amarruzzo@gmail.com>
License: Copyright © 2026 Andrea Marruzzo
Requires-Python: >=3.10
License-File: LICENSE
Requires-Dist: PyYAML>=6.0
Requires-Dist: colorama>=0.4.6
Dynamic: license-file
